scEasyMode/__init__.py
scEasyMode/clusterplot.py
scEasyMode/genotyping.py
scEasyMode/mousefilter.py
scEasyMode/pymulti.py
scEasyMode/sceasy.py
scEasyMode-1.0.1.dist-info/LICENSE
scEasyMode-1.0.1.dist-info/METADATA
scEasyMode-1.0.1.dist-info/WHEEL
scEasyMode-1.0.1.dist-info/top_level.txt
scEasyMode-1.0.1.dist-info/RECORD
