Metadata-Version: 2.1
Name: scEasyMode
Version: 1.0.1
Summary: Wrappers for automating single cell workflows in python
Home-page: https://github.com/johnnyUCSF/scEasyMode
Author: Johnny Yu
Author-email: johnny.yu@ucsf.edu
License: UNKNOWN
Platform: UNKNOWN
Classifier: Programming Language :: Python :: 3
Classifier: License :: OSI Approved :: MIT License
Classifier: Operating System :: OS Independent
Requires-Python: >=3.6
Requires-Dist: scanpy (==1.6.0)
Requires-Dist: pandas (==1.1.4)
Requires-Dist: matplotlib (==3.3.2)
Requires-Dist: seaborn (==0.11.0)
Requires-Dist: biopython (==1.78)
Requires-Dist: scipy (==1.5.4)
Requires-Dist: scikit-learn (==0.23.2)
